smartcore-0.1.0.dist-info/METADATA
smartcore-0.1.0.dist-info/WHEEL
smartcore/naive_bayes/__init__.py
smartcore/naive_bayes/__pycache__/__init__.cpython-38.pyc
smartcore/__init__.py
smartcore/tests/test_naive_bayes.py
smartcore/tests/__pycache__/test_naive_bayes.cpython-38-pytest-6.2.2.pyc
smartcore/tests/__pycache__/test_naive_bayes.cpython-38-pytest-6.2.1.pyc
smartcore/__pycache__/__init__.cpython-38.pyc
smartcore/smartcore.cpython-38-x86_64-linux-gnu.so
smartcore-0.1.0.dist-info/RECORD
