Metadata-Version: 2.1
Name: smartcore
Version: 0.1.0
Summary: Python bindings for smartcore, a machine learning library written in rust.
Author: SmartCore Developers
License: Apache-2.0
